artifact_filesystem_store-0.3.0.dist-info/licenses/LICENSE
artifact_store/__init__.py
artifact_store/cli.py
artifact_filesystem_store-0.3.0.dist-info/METADATA
artifact_filesystem_store-0.3.0.dist-info/WHEEL
artifact_filesystem_store-0.3.0.dist-info/entry_points.txt
artifact_filesystem_store-0.3.0.dist-info/top_level.txt
artifact_filesystem_store-0.3.0.dist-info/RECORD
