Metadata-Version: 2.4
Name: artifact-filesystem-store
Version: 0.3.0
Summary: A tool for storing and retrieving artifacts to a local filesystem backend storage.
Author-email: Patrick Boettcher <p@yai.se>
License: MIT
Project-URL: Homepage, https://github.com/pboettch/artifact-store
Requires-Python: >=3.8
License-File: LICENSE
Provides-Extra: dev
Requires-Dist: pytest>=7.0; extra == "dev"
Requires-Dist: pytest-cov; extra == "dev"
Requires-Dist: pyfakefs; extra == "dev"
Requires-Dist: black; extra == "dev"
Requires-Dist: flake8; extra == "dev"
Requires-Dist: bumpver; extra == "dev"
Requires-Dist: build; extra == "dev"
Requires-Dist: twine; extra == "dev"
Dynamic: license-file
